Workbook

Sheet Supuestos
A1: Proyecto ASHAB · Supuestos del modelo
A2: Las celdas en azul se pueden modificar: todo el libro se recalcula solo. Valores en USD salvo indicación.
A3: Supuesto | B3: Valor | C3: Nota
A4: Tipo de cambio ARS por USD | B4: 1450 | C4: Supuesto: actualizar al día de uso
A5: Kg netos por contenedor 40' | B5: 24000 | C5: Bolsas de 1 kg en cajas de 10 kg, contenedor seco de 40 pies
A6: Costo yerba empacada en planta (USD/kg) | B6: 1.55 | C6: Precio del cliente puesto en planta, a confirmar con la yerbatera
A7: Packaging de marca ASHAB bilingüe (USD/kg) | B7: 0.1 | C7: Extra sobre el packaging estándar
A8: Flete interno Misiones a Buenos Aires (USD/contenedor) | B8: 2400 | C8: Aprox. 1.100 km
A9: Gastos de exportación (USD/contenedor) | B9: 1600 | C9: Despachante, THC origen, documentación, precintos
A10: Flete marítimo Buenos Aires a Beirut/Jebel Ali (USD/contenedor) | B10: 4200 | C10: Incluye recargo por riesgo de zona; cotizar con naviera
A11: Prima de seguro de carga (% del valor asegurado) | B11: 0.006
A12: Valor asegurado (multiplicador sobre CIF) | B12: 1.1 | C12: Práctica habitual: CIF + 10%
A13: Derechos de exportación (% sobre FOB) | B13: 0 | C13: Supuesto 0%: verificar alícuota vigente en ARCA
A14: Precio de venta CIF (USD/kg) | B14: 2.55 | C14: Equivale a unos 2,36 USD/kg FOB
A15: Costo de carta de crédito (% de la venta) | B15: 0.008 | C15: Apertura, confirmación y gastos
A16: Gastos bancarios y cobranza (USD/contenedor) | B16: 300
A17: Seña obligatoria para confirmar el pedido (% de la venta) | B17: 0.5 | C17: Se cobra antes de producir; el saldo, antes de cargar el contenedor
A18: Honorario de éxito de Rumbo Global (% de la venta) | B18: 0.03 | C18: Se cobra solo por embarque cobrado
A19: Contenedores año 1 | B19: 6 | C19: Primer embarque en el mes 7 y luego uno por mes
A20: Contenedores año 2 | B20: 14
A21: Contenedores año 3 | B21: 24
A22: Mantenimiento web y sistema (USD/año, años 2 y 3) | B22: 600
A23: Agente comercial en destino (USD/año, años 2 y 3) | B23: 12000
A24: Feria anual (USD/año, años 2 y 3) | B24: 8000
A25: Consultoría de seguimiento (USD/año, años 2 y 3) | B25: 6000
A26: Imprevistos sobre inversión inicial (%) | B26: 0.05

Sheet Costo por contenedor
A1: Costo y margen de un contenedor 40' (24 toneladas)
A2: Del precio de planta al cobro en destino
A3: Concepto | B3: USD | C3: USD por kg
A4: Yerba empacada en planta | B4: =Supuestos!$B$5*Supuestos!$B$6 | C4: =B4/Supuestos!$B$5
A5: Packaging de marca bilingüe | B5: =Supuestos!$B$5*Supuestos!$B$7 | C5: =B5/Supuestos!$B$5
A6: Flete interno a Buenos Aires | B6: =Supuestos!$B$8 | C6: =B6/Supuestos!$B$5
A7: Gastos de exportación | B7: =Supuestos!$B$9 | C7: =B7/Supuestos!$B$5
A8: Derechos de exportación | B8: =SUM(B4:B7)*Supuestos!$B$13 | C8: =B8/Supuestos!$B$5
A9: COSTO FOB | B9: =SUM(B4:B8) | C9: =B9/Supuestos!$B$5
A10: Flete marítimo | B10: =Supuestos!$B$10 | C10: =B10/Supuestos!$B$5
A11: Seguro de carga | B11: =(B9+B10)*Supuestos!$B$12*Supuestos!$B$11 | C11: =B11/Supuestos!$B$5
A12: COSTO CIF | B12: =B9+B10+B11 | C12: =B12/Supuestos!$B$5
A13: Venta CIF al importador | B13: =Supuestos!$B$5*Supuestos!$B$14 | C13: =B13/Supuestos!$B$5
A14: Carta de crédito | B14: =B13*Supuestos!$B$15 | C14: =B14/Supuestos!$B$5
A15: Gastos bancarios y cobranza | B15: =Supuestos!$B$16 | C15: =B15/Supuestos!$B$5
A16: Honorario de éxito de Rumbo Global | B16: =B13*Supuestos!$B$18 | C16: =B16/Supuestos!$B$5
A17: COSTO TOTAL | B17: =B12+B14+B15+B16 | C17: =B17/Supuestos!$B$5
A18: MARGEN NETO POR CONTENEDOR | B18: =B13-B17 | C18: =B18/Supuestos!$B$5
A19: Margen sobre ventas | B19: =B18/B13
A20: Precio FOB equivalente (USD/kg) | B20: =(B13-B10-B11)/Supuestos!$B$5

Sheet Inversión inicial
A1: Inversión inicial del proyecto
A2: Se paga una sola vez durante el primer año
A3: Rubro | B3: USD | C3: Detalle
A4: Estudio de mercado y plan de exportación (consultora) | B4: 8000 | C4: Diagnóstico, selección de países, precios y plan a 3 años
A5: Registro de marca ASHAB (Argentina, Siria, Líbano, Jordania, EAU) | B5: 6500 | C5: Clase 30; tasas y honorarios de agentes locales
A6: Diseño de packaging y etiquetas en español, inglés y árabe | B6: 3500 | C6: Incluye adaptación de gráfica y pruebas de impresión
A7: Habilitaciones, análisis de laboratorio y certificados | B7: 2800 | C7: RNE, RNPA, análisis, certificado de origen y sanitarios
A8: Certificación halal (recomendada) | B8: 2500 | C8: Facilita el ingreso a cadenas y distribuidores
A9: Registros y trámites sanitarios en destino | B9: 4000 | C9: Agentes locales en los cuatro países
A10: Sitio web trilingüe y sistema de clientes (desarrollo) | B10: 5500 | C10: Español, inglés y árabe; inicio de sesión con DNI
A11: Dominio, hosting y mantenimiento (primer año) | B11: 600
A12: Viaje de prospección: 2 personas, Dubái y Beirut, 10 días | B12: 9000 | C12: Pasajes, hotel, traslados y reuniones
A13: Muestras y courier internacional | B13: 2000 | C13: Hasta 30 muestras de 1 kg
A14: Feria Gulfood Dubái (stand compartido) | B14: 12000 | C14: Participación junto a otras empresas argentinas
A15: Consultoría de implementación (6 meses) | B15: 13800 | C15: 6 cuotas de 2.300 USD
A16: Seguro de crédito a la exportación y contingencias | B16: 2000 | C16: Cobertura de riesgo comercial y político
A17: Subtotal | B17: =SUM(B4:B16)
A18: Imprevistos | B18: =B17*Supuestos!$B$26
A19: INVERSIÓN INICIAL TOTAL (USD) | B19: =B17+B18
A20: Inversión inicial total (ARS) | B20: =B19*Supuestos!$B$4
A21: Capital de trabajo recomendado (2 contenedores, con seña del 50 %) | B21: =('Costo por contenedor'!B17-'Costo por contenedor'!B13*Supuestos!$B$17)*2
A22: NECESIDAD MÁXIMA DE FINANCIAMIENTO (USD) | B22: =B19+B21

Sheet Proyección 3 años
A1: Proyección a 3 años
A2: No incluye impuesto a las ganancias ni costo financiero. El IVA de exportación está exento (se recupera el crédito fiscal).
A3: Concepto | B3: Año 1 | C3: Año 2 | D3: Año 3
A4: Contenedores de 40' | B4: =Supuestos!$B$19 | C4: =Supuestos!$B$20 | D4: =Supuestos!$B$21
A5: Ingresos por ventas | B5: =B4*'Costo por contenedor'!$B$13 | C5: =C4*'Costo por contenedor'!$B$13 | D5: =D4*'Costo por contenedor'!$B$13
A6: Costos variables (producto, logística, comisiones) | B6: =B4*'Costo por contenedor'!$B$17 | C6: =C4*'Costo por contenedor'!$B$17 | D6: =D4*'Costo por contenedor'!$B$17
A7: Margen de contribución | B7: =B5-B6 | C7: =C5-C6 | D7: =D5-D6
A8: Costos fijos (web, agente, feria, seguimiento) | B8: 0 | C8: =Supuestos!$B$22+Supuestos!$B$23+Supuestos!$B$24+Supuestos!$B$25 | D8: =Supuestos!$B$22+Supuestos!$B$23+Supuestos!$B$24+Supuestos!$B$25
A9: Inversión inicial | B9: ='Inversión inicial'!$B$19 | C9: 0 | D9: 0
A10: FLUJO NETO DEL AÑO | B10: =B7-B8-B9 | C10: =C7-C8-C9 | D10: =D7-D8-D9
A11: FLUJO ACUMULADO | B11: =B10 | C11: =B11+C10 | D11: =C11+D10
A13: Recupero de la inversión (meses aprox.) | B13: =IF(B11>=0,12*B9/B7,12+(-B11)/(C10/12))

Sheet Escenarios
A1: Escenarios a 3 años
A2: Se modifican el precio de venta y el volumen respecto del caso base
A3: Escenario | B3: Variación de precio | C3: Variación de volumen | D3: Margen por contenedor | E3: Flujo acumulado a 3 años
A4: Pesimista | B4: -0.1 | C4: -0.3 | D4: =Supuestos!$B$5*Supuestos!$B$14*(1+B4)*(1-Supuestos!$B$15-Supuestos!$B$18)-('Costo por contenedor'!$B$12+'Costo por contenedor'!$B$15) | E4: =D4*(Supuestos!$B$19+Supuestos!$B$20+Supuestos!$B$21)*(1+C4)-'Inversión inicial'!$B$19-2*(Supuestos!$B$22+Supuestos!$B$23+Supuestos!$B$24+Supuestos!$B$25)
A5: Base | B5: 0 | C5: 0 | D5: =Supuestos!$B$5*Supuestos!$B$14*(1+B5)*(1-Supuestos!$B$15-Supuestos!$B$18)-('Costo por contenedor'!$B$12+'Costo por contenedor'!$B$15) | E5: =D5*(Supuestos!$B$19+Supuestos!$B$20+Supuestos!$B$21)*(1+C5)-'Inversión inicial'!$B$19-2*(Supuestos!$B$22+Supuestos!$B$23+Supuestos!$B$24+Supuestos!$B$25)
A6: Optimista | B6: 0.05 | C6: 0.2 | D6: =Supuestos!$B$5*Supuestos!$B$14*(1+B6)*(1-Supuestos!$B$15-Supuestos!$B$18)-('Costo por contenedor'!$B$12+'Costo por contenedor'!$B$15) | E6: =D6*(Supuestos!$B$19+Supuestos!$B$20+Supuestos!$B$21)*(1+C6)-'Inversión inicial'!$B$19-2*(Supuestos!$B$22+Supuestos!$B$23+Supuestos!$B$24+Supuestos!$B$25)
